Metadata-Version: 1.0
Name: probability-sy
Version: 0.1
Summary: Gaussian distributions
Home-page: UNKNOWN
Author: Shreedhar Sampath Kumar
Author-email: shreedhar022@gmail.com
License: UNKNOWN
Platform: UNKNOWN
